phold/__init__.py
phold/cnn/cnn_chkpnt/model.pt
phold/cnn/cnn_chkpnt_finetune/phold_db_model.pth
phold/cnn/cnn_chkpnt_finetune/vanilla_model.pth
phold/databases/db.py
phold/features/autotune.py
phold/features/create_foldseek_db.py
phold/features/predict_3Di.py
phold/features/query_remote_3Di.py
phold/features/run_foldseek.py
phold/io/handle_genbank.py
phold/io/sub_db_outputs.py
phold/plot/plot.py
phold/results/topfunction.py
phold/subcommands/compare.py
phold/subcommands/predict.py
phold/utils/CITATION
phold/utils/VERSION
phold/utils/constants.py
phold/utils/external_tools.py
phold/utils/util.py
phold/utils/validation.py
phold-1.2.2.dist-info/licenses/AUTHORS.md
phold-1.2.2.dist-info/licenses/LICENSE
phold-1.2.2.dist-info/METADATA
phold-1.2.2.dist-info/WHEEL
phold-1.2.2.dist-info/entry_points.txt
phold-1.2.2.dist-info/top_level.txt
phold-1.2.2.dist-info/zip-safe
phold-1.2.2.dist-info/RECORD
