Metadata-Version: 2.4
Name: phold
Version: 1.2.2
Summary: Phage Annotations using Protein Structures
Author-email: George Bouras <george.bouras@adelaide.edu.au>
Project-URL: Homepage, https://github.com/gbouras13/phold
Project-URL: Documentation, https://phold.readthedocs.io/en/latest
Keywords: keyword,are,cool
Classifier: Development Status :: 4 - Beta
Classifier: Environment :: Console
Classifier: License :: OSI Approved :: MIT License
Classifier: Natural Language :: English
Classifier: Topic :: Scientific/Engineering :: Bio-Informatics
Classifier: Operating System :: OS Independent
Classifier: Programming Language :: Python
Classifier: Programming Language :: Python :: 3
Classifier: Programming Language :: Python :: 3.8
Classifier: Programming Language :: Python :: 3.9
Classifier: Programming Language :: Python :: 3.10
Classifier: Programming Language :: Python :: 3.11
Classifier: Programming Language :: Python :: 3.12
Classifier: Programming Language :: Python :: 3.13
Classifier: Programming Language :: Python :: 3.14
Requires-Python: <4,>=3.8
License-File: LICENSE
License-File: AUTHORS.md
Requires-Dist: click>=8.0.0
Requires-Dist: loguru>=0.5.3
Requires-Dist: pyyaml>=6.0
Requires-Dist: pandas>=1.4.2
Requires-Dist: biopython>=1.80
Requires-Dist: datasets>=2.15
Requires-Dist: requests>=2.25
Requires-Dist: sentencepiece>=0.1.99
Requires-Dist: protobuf>=6.0
Requires-Dist: transformers>=4.34
Requires-Dist: torch>=2.1.2
Requires-Dist: pyrodigal-gv>=0.3.1
Requires-Dist: pyarrow>=14.0.0
Requires-Dist: alive-progress>=3.0.1
Requires-Dist: numpy<2,>=1.20
Requires-Dist: pycirclize>=0.3.1
Requires-Dist: h5py>=3.5
Requires-Dist: tqdm>=4.35.0
Provides-Extra: lint
Requires-Dist: isort; extra == "lint"
Requires-Dist: black; extra == "lint"
Provides-Extra: test
Requires-Dist: pytest>=6.2.5; extra == "test"
Requires-Dist: pytest-cov>=3.0.0; extra == "test"
Provides-Extra: exe
Requires-Dist: setuptools; extra == "exe"
Requires-Dist: wheel; extra == "exe"
Requires-Dist: build; extra == "exe"
Dynamic: license-file
